tkintergalactic/__init__.py
tkintergalactic/diff.py
tkintergalactic/events.py
tkintergalactic/widgets.py
tkintergalactic-0.0.1.dist-info/licenses/LICENCE
tkintergalactic-0.0.1.dist-info/METADATA
tkintergalactic-0.0.1.dist-info/WHEEL
tkintergalactic-0.0.1.dist-info/top_level.txt
tkintergalactic-0.0.1.dist-info/RECORD
