Metadata-Version: 2.4
Name: tkintergalactic
Version: 0.0.1
Summary: Delarative Tcl/Tk
Author-email: Oliver Russell <ojhrussell@gmail.com>
Maintainer-email: Oliver Russell <ojhrussell@gmail.com>
Project-URL: homepage, https://leontrolski.github.io/
Keywords: TCL,TK,UI
Classifier: Programming Language :: Python
Requires-Python: >=3.12
License-File: LICENCE
Provides-Extra: dev
Requires-Dist: pytest==8.3.5; extra == "dev"
Requires-Dist: ruff==0.11.2; extra == "dev"
Requires-Dist: mypy==1.15.0; extra == "dev"
Requires-Dist: ocdiff==0.0.33; extra == "dev"
Requires-Dist: rich==14.0.0; extra == "dev"
Dynamic: license-file
